{"cameraMode":{"drawMode":0,"name":"Shaded","section":"Shading Mode"},"sceneLighting":true,"audioPlay":false,"sceneViewState":{"m_AlwaysRefresh":false,"showFog":true,"showSkybox":true,"showFlares":true,"showImageEffects":true,"showParticleSystems":true,"showVisualEffectGraphs":true,"m_FxEnabled":true},"in2DMode":false,"pivot":{"x":0.8436266183853149,"y":7.5864033699035648,"z":92.28734588623047},"rotation":{"x":-0.07292400300502777,"y":-0.06442875415086746,"z":0.002334450138732791,"w":-0.9964087605476379},"size":6.727514743804932,"orthographic":false}